<Properties StartupConfiguration="{2D1DAC1C-491A-4965-A55A-AFC7C3661E95}|Default">
  <MonoDevelop.Ide.Workbench ActiveDocument="Customer.cs">
    <Files>
      <File FileName="Program.cs" Line="1" Column="1" />
      <File FileName="Customer.cs" Line="30" Column="2" />
    </Files>
    <Pads>
      <Pad Id="ProjectPad">
        <State name="__root__">
          <Node name="numberOne" expanded="True" selected="True">
            <Node name="numberOne" expanded="True" />
          </Node>
        </State>
      </Pad>
    </Pads>
  </MonoDevelop.Ide.Workbench>
  <MonoDevelop.Ide.ItemProperties.numberOne PreferredExecutionTarget="MonoDevelop.Default" />
  <MonoDevelop.Ide.DebuggingService.PinnedWatches />
  <MonoDevelop.Ide.Workspace ActiveConfiguration="Debug" />
  <MonoDevelop.Ide.DebuggingService.Breakpoints>
    <BreakpointStore />
  </MonoDevelop.Ide.DebuggingService.Breakpoints>
  <MultiItemStartupConfigurations />
</Properties>